purposefully_malicious/__init__.py
purposefully_malicious-1.0.0.dist-info/LICENSE
purposefully_malicious-1.0.0.dist-info/METADATA
purposefully_malicious-1.0.0.dist-info/WHEEL
purposefully_malicious-1.0.0.dist-info/top_level.txt
purposefully_malicious-1.0.0.dist-info/RECORD
